{
  "metadata": {
    "dataVersion": "2",
    "matchId": "NA1_5509711409",
    "participants": [
      "APA28lrTMAindqS2JtK37LpHssR84c5yA-rsROWLMl0lUibJqj-h3eJGCCdLYzi2F5TVI1puEFg29A",
      "C9cqY_f7CKLenYtaF88zJIDoOeKjsA0Tlm1c5zwYo-gsr1s0Dz_017Y6yO7q0poClRP9d1LihtZUKQ",
      "dgLaMbNO-4i_tjq3CxrBD7rt0Vd3352ekzoX8YrqYyMHd53ZQhl_cRv2m_k0Tbrlmz6MGTMerz3rtg",
      "y6dT8B0hQr_O9RAGcPesmwDLfgbggO2QVllgr8WoWUFkPhyuUuVnO-aK-bEDQtMLZ-hOrRfZoomlCg",
      "uOeA9Vr1KWCfS8423pKuTp4BvX6KHCYj2tVRzshc6HKRGCTTAEUe2sgmJGIJxdWLSZ3gIrqak560-w",
      "3tYeKv0VM46d3uIXQAzdZM-lrcdAN0bkSE4DYPNkkzRRc4NzoH7X_Hjz7u_0R8qyQqMP2DCUz3ergg",
      "QvvuKSyYjC8oDYdsdCaI-e7pjK8s-t4XObnsdmRHRGntC6eVybdawIB0_HdfBI0UOe0gysX-GH63Ng",
      "aJRqb8vC0me7j4Ovn_yLs98-oO2oLsbBTmEyrKVCGRQM_AoHWPLIyHF5giged-eJ6k4sxeaDscYIzA",
      "eLsvz5Jk0dgoQifrZL6IlXr30qpNjoMAo5-L7jNqdM8zSjUGTebwUgIKvwWKFb7vp48MhevPsgZZaQ",
      "rOmEEynItfQpKDMyxFt5nVkn6xmv_fdy3CuJrbD0D-CFT5YFLkng3xUvkMuIgD9RuEgHbcet7ky4cw"
    ]
  },
  "info": {
    "endOfGameResult": "GameComplete",
    "frameInterval": 60000,
    "frames": [
      {
        "events": [
          {
            "realTimestamp": 1773163427605,
            "timestamp": 0,
            "type": "PAUSE_END"
          },
          {
            "itemId": 3865,
            "participantId": 0,
            "timestamp": 0,
            "type": "ITEM_PURCHASED"
          },
          {
            "itemId": 3865,
            "participantId": 0,
            "timestamp": 0,
            "type": "ITEM_PURCHASED"
          }
        ],
        "participantFrames": {
          "1": {
            "championStats": {
              "abilityHaste": 0,
              "abilityPower": 0,
              "armor": 23,
              "armorPen": 0,
              "armorPenPercent": 0,
              "attackDamage": 53,
              "attackSpeed": 100,
              "bonusArmorPenPercent": 0,
              "bonusMagicPenPercent": 0,
              "ccReduction": 0,
              "cooldownReduction": 0,
              "health": 607,
              "healthMax": 607,
              "healthRegen": 12,
              "lifesteal": 0,
              "magicPen": 0,
              "magicPenPercent": 0,
              "magicResist": 32,
              "movementSpeed": 335,
              "omnivamp": 0,
              "physicalVamp": 0,
              "power": 475,
              "powerMax": 475,
              "powerRegen": 16,
              "spellVamp": 0
            },
            "currentGold": 500,
            "damageStats": {
              "magicDamageDone": 0,
              "magicDamageDoneToChampions": 0,
              "magicDamageTaken": 0,
              "physicalDamageDone": 0,
              "physicalDamageDoneToChampions": 0,
              "physicalDamageTaken": 0,
              "totalDamageDone": 0,
              "totalDamageDoneToChampions": 0,
              "totalDamageTaken": 0,
              "trueDamageDone": 0,
              "trueDamageDoneToChampions": 0,
              "trueDamageTaken": 0
            },
            "goldPerSecond": 0,
            "jungleMinionsKilled": 0,
            "level": 1,
            "minionsKilled": 0,
            "participantId": 1,
            "position": {
              "x": 603,
              "y": 611
            },
            "timeEnemySpentControlled": 0,
            "totalGold": 500,
            "xp": 0
          },
          "2": {
            "championStats": {
              "abilityHaste": 0,
              "abilityPower": 0,
              "armor": 30,
              "armorPen": 0,
              "armorPenPercent": 0,
              "attackDamage": 68,
              "attackSpeed": 100,
              "bonusArmorPenPercent": 0,
              "bonusMagicPenPercent": 0,
              "ccReduction": 0,
              "cooldownReduction": 0,
              "health": 658,
              "healthMax": 658,
              "healthRegen": 17,
              "lifesteal": 0,
              "magicPen": 0,
              "magicPenPercent": 0,
              "magicResist": 36,
              "movementSpeed": 335,
              "omnivamp": 0,
              "physicalVamp": 0,
              "power": 400,
              "powerMax": 400,
              "powerRegen": 15,
              "spellVamp": 0
            },
            "currentGold": 500,
            "damageStats": {
              "magicDamageDone": 0,
              "magicDamageDoneToChampions": 0,
              "magicDamageTaken": 0,
              "physicalDamageDone": 0,
              "physicalDamageDoneToChampions": 0,
              "physicalDamageTaken": 0,
              "totalDamageDone": 0,
              "totalDamageDoneToChampions": 0,
              "totalDamageTaken": 0,
              "trueDamageDone": 0,
              "trueDamageDoneToChampions": 0,
              "trueDamageTaken": 0
            },
            "goldPerSecond": 0,
            "jungleMinionsKilled": 0,
            "level": 1,
            "minionsKilled": 0,
            "participantId": 2,
            "position": {
              "x": 662,
              "y": 285
            },
            "timeEnemySpentControlled": 0,
            "totalGold": 500,
            "xp": 0
          },
          "3": {
            "championStats": {
              "abilityHaste": 0,
              "abilityPower": 0,
              "armor": 22,
              "armorPen": 0,
              "armorPenPercent": 0,
              "attackDamage": 55,
              "attackSpeed": 100,
              "bonusArmorPenPercent": 0,
              "bonusMagicPenPercent": 0,
              "ccReduction": 0,
              "cooldownReduction": 0,
              "health": 590,
              "healthMax": 590,
              "healthRegen": 11,
              "lifesteal": 0,
              "magicPen": 0,
              "magicPenPercent": 0,
              "magicResist": 30,
              "movementSpeed": 340,
              "omnivamp": 0,
              "physicalVamp": 0,
              "power": 469,
              "powerMax": 469,
              "powerRegen": 16,
              "spellVamp": 0
            },
            "currentGold": 500,
            "damageStats": {
              "magicDamageDone": 0,
              "magicDamageDoneToChampions": 0,
              "magicDamageTaken": 0,
              "physicalDamageDone": 0,
              "physicalDamageDoneToChampions": 0,
              "physicalDamageTaken": 0,
              "totalDamageDone": 0,
              "totalDamageDoneToChampions": 0,
              "totalDamageTaken": 0,
              "trueDamageDone": 0,
              "trueDamageDoneToChampions": 0,
              "trueDamageTaken": 0
            },
            "goldPerSecond": 0,
            "jungleMinionsKilled": 0,
            "level": 1,
            "minionsKilled": 0,
            "participantId": 3,
            "position": {
              "x": 362,
              "y": 135
            },
            "timeEnemySpentControlled": 0,
            "totalGold": 500,
            "xp": 0
          },
          "4": {
            "championStats": {
              "abilityHaste": 0,
              "abilityPower": 0,
              "armor": 32,
              "armorPen": 0,
              "armorPenPercent": 0,
              "attackDamage": 60,
              "attackSpeed": 100,
              "bonusArmorPenPercent": 0,
              "bonusMagicPenPercent": 0,
              "ccReduction": 0,
              "cooldownReduction": 0,
              "health": 590,
              "healthMax": 590,
              "healthRegen": 13,
              "lifesteal": 0,
              "magicPen": 0,
              "magicPenPercent": 0,
              "magicResist": 32,
              "movementSpeed": 345,
              "omnivamp": 0,
              "physicalVamp": 0,
              "power": 125,
              "powerMax": 125,
              "powerRegen": 0,
              "spellVamp": 0
            },
            "currentGold": 500,
            "damageStats": {
              "magicDamageDone": 0,
              "magicDamageDoneToChampions": 0,
              "magicDamageTaken": 0,
              "physicalDamageDone": 0,
              "physicalDamageDoneToChampions": 0,
              "physicalDamageTaken": 0,
              "totalDamageDone": 0,
              "totalDamageDoneToChampions": 0,
              "totalDamageTaken": 0,
              "trueDamageDone": 0,
              "trueDamageDoneToChampions": 0,
              "trueDamageTaken": 0
            },
            "goldPerSecond": 0,
            "jungleMinionsKilled": 0,
            "level": 1,
            "minionsKilled": 0,
            "participantId": 4,
            "position": {
              "x": 130,
              "y": 401
            },
            "timeEnemySpentControlled": 0,
            "totalGold": 500,
            "xp": 0
          },
          "5": {
            "championStats": {
              "abilityHaste": 0,
              "abilityPower": 0,
              "armor": 26,
              "armorPen": 0,
              "armorPenPercent": 0,
              "attackDamage": 50,
              "attackSpeed": 100,
              "bonusArmorPenPercent": 0,
              "bonusMagicPenPercent": 0,
              "ccReduction": 0,
              "cooldownReduction": 0,
              "health": 600,
              "healthMax": 600,
              "healthRegen": 16,
              "lifesteal": 0,
              "magicPen": 0,
              "magicPenPercent": 0,
              "magicResist": 30,
              "movementSpeed": 330,
              "omnivamp": 0,
              "physicalVamp": 0,
              "power": 360,
              "powerMax": 360,
              "powerRegen": 28,
              "spellVamp": 0
            },
            "currentGold": 100,
            "damageStats": {
              "magicDamageDone": 0,
              "magicDamageDoneToChampions": 0,
              "magicDamageTaken": 0,
              "physicalDamageDone": 0,
              "physicalDamageDoneToChampions": 0,
              "physicalDamageTaken": 0,
              "totalDamageDone": 0,
              "totalDamageDoneToChampions": 0,
              "totalDamageTaken": 0,
              "trueDamageDone": 0,
              "trueDamageDoneToChampions": 0,
              "trueDamageTaken": 0
            },
            "goldPerSecond": 30,
            "jungleMinionsKilled": 0,
            "level": 1,
            "minionsKilled": 0,
            "participantId": 5,
            "position": {
              "x": 298,
              "y": 675
            },
            "timeEnemySpentControlled": 0,
            "totalGold": 500,
            "xp": 0
          },
          "6": {
            "championStats": {
              "abilityHaste": 0,
              "abilityPower": 0,
              "armor": 40,
              "armorPen": 0,
              "armorPenPercent": 0,
              "attackDamage": 62,
              "attackSpeed": 100,
              "bonusArmorPenPercent": 0,
              "bonusMagicPenPercent": 0,
              "ccReduction": 0,
              "cooldownReduction": 0,
              "health": 665,
              "healthMax": 665,
              "healthRegen": 14,
              "lifesteal": 0,
              "magicPen": 0,
              "magicPenPercent": 0,
              "magicResist": 28,
              "movementSpeed": 335,
              "omnivamp": 0,
              "physicalVamp": 0,
              "power": 280,
              "powerMax": 280,
              "powerRegen": 14,
              "spellVamp": 0
            },
            "currentGold": 500,
            "damageStats": {
              "magicDamageDone": 0,
              "magicDamageDoneToChampions": 0,
              "magicDamageTaken": 0,
              "physicalDamageDone": 0,
              "physicalDamageDoneToChampions": 0,
              "physicalDamageTaken": 0,
              "totalDamageDone": 0,
              "totalDamageDoneToChampions": 0,
              "totalDamageTaken": 0,
              "trueDamageDone": 0,
              "trueDamageDoneToChampions": 0,
              "trueDamageTaken": 0
            },
            "goldPerSecond": 0,
            "jungleMinionsKilled": 0,
            "level": 1,
            "minionsKilled": 0,
            "participantId": 6,
            "position": {
              "x": 14103,
              "y": 14195
            },
            "timeEnemySpentControlled": 0,
            "totalGold": 500,
            "xp": 0
          },
          "7": {
            "championStats": {
              "abilityHaste": 0,
              "abilityPower": 0,
              "armor": 38,
              "armorPen": 0,
              "armorPenPercent": 0,
              "attackDamage": 68,
              "attackSpeed": 100,
              "bonusArmorPenPercent": 0,
              "bonusMagicPenPercent": 0,
              "ccReduction": 0,
              "cooldownReduction": 0,
              "health": 655,
              "healthMax": 655,
              "healthRegen": 16,
              "lifesteal": 0,
              "magicPen": 0,
              "magicPenPercent": 0,
              "magicResist": 32,
              "movementSpeed": 340,
              "omnivamp": 0,
              "physicalVamp": 0,
              "power": 410,
              "powerMax": 410,
              "powerRegen": 23,
              "spellVamp": 0
            },
            "currentGold": 500,
            "damageStats": {
              "magicDamageDone": 0,
              "magicDamageDoneToChampions": 0,
              "magicDamageTaken": 0,
              "physicalDamageDone": 0,
              "physicalDamageDoneToChampions": 0,
              "physicalDamageTaken": 0,
              "totalDamageDone": 0,
              "totalDamageDoneToChampions": 0,
              "totalDamageTaken": 0,
              "trueDamageDone": 0,
              "trueDamageDoneToChampions": 0,
              "trueDamageTaken": 0
            },
            "goldPerSecond": 0,
            "jungleMinionsKilled": 0,
            "level": 1,
            "minionsKilled": 0,
            "participantId": 7,
            "position": {
              "x": 14426,
              "y": 14170
            },
            "timeEnemySpentControlled": 0,
            "totalGold": 500,
            "xp": 0
          },
          "8": {
            "championStats": {
              "abilityHaste": 0,
              "abilityPower": 0,
              "armor": 34,
              "armorPen": 0,
              "armorPenPercent": 0,
              "attackDamage": 67,
              "attackSpeed": 100,
              "bonusArmorPenPercent": 0,
              "bonusMagicPenPercent": 0,
              "ccReduction": 0,
              "cooldownReduction": 0,
              "health": 650,
              "healthMax": 650,
              "healthRegen": 18,
              "lifesteal": 12,
              "magicPen": 0,
              "magicPenPercent": 0,
              "magicResist": 32,
              "movementSpeed": 350,
              "omnivamp": 0,
              "physicalVamp": 0,
              "power": 326,
              "powerMax": 326,
              "powerRegen": 14,
              "spellVamp": 0
            },
            "currentGold": 500,
            "damageStats": {
              "magicDamageDone": 0,
              "magicDamageDoneToChampions": 0,
              "magicDamageTaken": 0,
              "physicalDamageDone": 0,
              "physicalDamageDoneToChampions": 0,
              "physicalDamageTaken": 0,
              "totalDamageDone": 0,
              "totalDamageDoneToChampions": 0,
              "totalDamageTaken": 0,
              "trueDamageDone": 0,
              "trueDamageDoneToChampions": 0,
              "trueDamageTaken": 0
            },
            "goldPerSecond": 0,
            "jungleMinionsKilled": 0,
            "level": 1,
            "minionsKilled": 0,
            "participantId": 8,
            "position": {
              "x": 14321,
              "y": 14673
            },
            "timeEnemySpentControlled": 0,
            "totalGold": 500,
            "xp": 0
          },
          "9": {
            "championStats": {
              "abilityHaste": 0,
              "abilityPower": 0,
              "armor": 27,
              "armorPen": 0,
              "armorPenPercent": 0,
              "attackDamage": 52,
              "attackSpeed": 100,
              "bonusArmorPenPercent": 0,
              "bonusMagicPenPercent": 0,
              "ccReduction": 0,
              "cooldownReduction": 0,
              "health": 610,
              "healthMax": 610,
              "healthRegen": 11,
              "lifesteal": 0,
              "magicPen": 0,
              "magicPenPercent": 0,
              "magicResist": 30,
              "movementSpeed": 325,
              "omnivamp": 0,
              "physicalVamp": 0,
              "power": 350,
              "powerMax": 350,
              "powerRegen": 14,
              "spellVamp": 0
            },
            "currentGold": 500,
            "damageStats": {
              "magicDamageDone": 0,
              "magicDamageDoneToChampions": 0,
              "magicDamageTaken": 0,
              "physicalDamageDone": 0,
              "physicalDamageDoneToChampions": 0,
              "physicalDamageTaken": 0,
              "totalDamageDone": 0,
              "totalDamageDoneToChampions": 0,
              "totalDamageTaken": 0,
              "trueDamageDone": 0,
              "trueDamageDoneToChampions": 0,
              "trueDamageTaken": 0
            },
            "goldPerSecond": 0,
            "jungleMinionsKilled": 0,
            "level": 1,
            "minionsKilled": 0,
            "participantId": 9,
            "position": {
              "x": 14589,
              "y": 14454
            },
            "timeEnemySpentControlled": 0,
            "totalGold": 500,
            "xp": 0
          },
          "10": {
            "championStats": {
              "abilityHaste": 0,
              "abilityPower": 0,
              "armor": 29,
              "armorPen": 0,
              "armorPenPercent": 0,
              "attackDamage": 54,
              "attackSpeed": 100,
              "bonusArmorPenPercent": 0,
              "bonusMagicPenPercent": 0,
              "ccReduction": 0,
              "cooldownReduction": 0,
              "health": 590,
              "healthMax": 590,
              "healthRegen": 13,
              "lifesteal": 0,
              "magicPen": 0,
              "magicPenPercent": 0,
              "magicResist": 30,
              "movementSpeed": 335,
              "omnivamp": 0,
              "physicalVamp": 0,
              "power": 365,
              "powerMax": 365,
              "powerRegen": 28,
              "spellVamp": 0
            },
            "currentGold": 100,
            "damageStats": {
              "magicDamageDone": 0,
              "magicDamageDoneToChampions": 0,
              "magicDamageTaken": 0,
              "physicalDamageDone": 0,
              "physicalDamageDoneToChampions": 0,
              "physicalDamageTaken": 0,
              "totalDamageDone": 0,
              "totalDamageDoneToChampions": 0,
              "totalDamageTaken": 0,
              "trueDamageDone": 0,
              "trueDamageDoneToChampions": 0,
              "trueDamageTaken": 0
            },
            "goldPerSecond": 30,
            "jungleMinionsKilled": 0,
            "level": 1,
            "minionsKilled": 0,
            "participantId": 10,
            "position": {
              "x": 14055,
              "y": 14493
            },
            "timeEnemySpentControlled": 0,
            "totalGold": 500,
            "xp": 0
          }
        },
        "timestamp": 0
      },
      {
        "events": [
          {
            "itemId": 3340,
            "participantId": 5,
            "timestamp": 1972,
            "type": "ITEM_PURCHASED"
          },
          {
            "itemId": 1056,
            "participantId": 3,
            "timestamp": 2105,
            "type": "ITEM_PURCHASED"
          },
          {
            "itemId": 2003,
            "participantId": 3,
            "timestamp": 2105,
            "type": "ITEM_PURCHASED"
          },
          {
            "itemId": 2003,
            "participantId": 3,
            "timestamp": 2105,
            "type": "ITEM_PURCHASED"
          },
          {
            "itemId": 2003,
            "participantId": 5,
            "timestamp": 2606,
            "type": "ITEM_PURCHASED"
          },
          {
            "itemId": 2003,
            "participantId": 5,
            "timestamp": 2940,
            "type": "ITEM_PURCHASED"
          },
          {
            "itemId": 1056,
            "participantId": 6,
            "timestamp": 3007,
            "type": "ITEM_PURCHASED"
          },
          {
            "itemId": 2003,
            "participantId": 6,
            "timestamp": 3007,
            "type": "ITEM_PURCHASED"
          },
          {
            "itemId": 2003,
            "participantId": 6,
            "timestamp": 3007,
            "type": "ITEM_PURCHASED"
          },
          {
            "itemId": 1056,
            "participantId": 1,
            "timestamp": 3775,
            "type": "ITEM_PURCHASED"
          },
          {
            "itemId": 2003,
            "participantId": 1,
            "timestamp": 3775,
            "type": "ITEM_PURCHASED"
          },
          {
            "itemId": 2003,
            "participantId": 1,
            "timestamp": 3775,
            "type": "ITEM_PURCHASED"
          },
          {
            "itemId": 3340,
            "participantId": 10,
            "timestamp": 4210,
            "type": "ITEM_PURCHASED"
          },
          {
            "itemId": 3340,
            "participantId": 1,
            "timestamp": 4243,
            "type": "ITEM_PURCHASED"
          },
          {
            "itemId": 2003,
            "participantId": 10,
            "timestamp": 4577,
            "type": "ITEM_PURCHASED"
          },
          {
            "itemId": 2003,
            "participantId": 10,
            "timestamp": 4844,
            "type": "ITEM_PURCHASED"
          },
          {
            "itemId": 1054,
            "participantId": 8,
            "timestamp": 6247,
            "type": "ITEM_PURCHASED"
          },
          {
            "itemId": 2003,
            "participantId": 8,
            "timestamp": 6247,
            "type": "ITEM_PURCHASED"
          },
          {
            "itemId": 1102,
            "participantId": 7,
            "timestamp": 6448,
            "type": "ITEM_PURCHASED"
          },
          {
            "levelUpType": "NORMAL",
            "participantId": 7,
            "skillSlot": 1,
            "timestamp": 7283,
            "type": "SKILL_LEVEL_UP"
          },
          {
            "itemId": 1101,
            "participantId": 2,
            "timestamp": 7550,
            "type": "ITEM_PURCHASED"
          },
          {
            "itemId": 1055,
            "participantId": 9,
            "timestamp": 7917,
            "type": "ITEM_PURCHASED"
          },
          {
            "itemId": 2003,
            "participantId": 9,
            "timestamp": 7917,
            "type": "ITEM_PURCHASED"
          },
          {
            "itemId": 3340,
            "participantId": 9,
            "timestamp": 8285,
            "type": "ITEM_PURCHASED"
          },
          {
            "levelUpType": "NORMAL",
            "participantId": 10,
            "skillSlot": 2,
            "timestamp": 18773,
            "type": "SKILL_LEVEL_UP"
          },
          {
            "creatorId": 7,
            "timestamp": 28728,
            "type": "WARD_PLACED",
            "wardType": "YELLOW_TRINKET"
          },
          {
            "levelUpType": "NORMAL",
            "participantId": 6,
            "skillSlot": 1,
            "timestamp": 30899,
            "type": "SKILL_LEVEL_UP"
          },
          {
            "levelUpType": "NORMAL",
            "participantId": 3,
            "skillSlot": 1,
            "timestamp": 32369,
            "type": "SKILL_LEVEL_UP"
          },
          {
            "creatorId": 9,
            "timestamp": 32736,
            "type": "WARD_PLACED",
            "wardType": "YELLOW_TRINKET"
          },
          {
            "levelUpType": "NORMAL",
            "participantId": 8,
            "skillSlot": 1,
            "timestamp": 34540,
            "type": "SKILL_LEVEL_UP"
          },
          {
            "levelUpType": "NORMAL",
            "participantId": 2,
            "skillSlot": 2,
            "timestamp": 36144,
            "type": "SKILL_LEVEL_UP"
          },
          {
            "creatorId": 2,
            "timestamp": 39016,
            "type": "WARD_PLACED",
            "wardType": "YELLOW_TRINKET"
          },
          {
            "levelUpType": "NORMAL",
            "participantId": 1,
            "skillSlot": 1,
            "timestamp": 46499,
            "type": "SKILL_LEVEL_UP"
          },
          {
            "creatorId": 8,
            "timestamp": 50775,
            "type": "WARD_PLACED",
            "wardType": "YELLOW_TRINKET"
          }
        ],
        "participantFrames": {
          "1": {
            "championStats": {
              "abilityHaste": 0,
              "abilityPower": 27,
              "armor": 23,
              "armorPen": 0,
              "armorPenPercent": 0,
              "attackDamage": 53,
              "attackSpeed": 110,
              "bonusArmorPenPercent": 0,
              "bonusMagicPenPercent": 0,
              "ccReduction": 0,
              "cooldownReduction": 0,
              "health": 762,
              "healthMax": 762,
              "healthRegen": 12,
              "lifesteal": 0,
              "magicPen": 0,
              "magicPenPercent": 0,
              "magicResist": 32,
              "movementSpeed": 335,
              "omnivamp": 0,
              "physicalVamp": 0,
              "power": 454,
              "powerMax": 500,
              "powerRegen": 16,
              "spellVamp": 0
            },
            "currentGold": 0,
            "damageStats": {
              "magicDamageDone": 26,
              "magicDamageDoneToChampions": 26,
              "magicDamageTaken": 0,
              "physicalDamageDone": 0,
              "physicalDamageDoneToChampions": 0,
              "physicalDamageTaken": 0,
              "totalDamageDone": 26,
              "totalDamageDoneToChampions": 26,
              "totalDamageTaken": 0,
              "trueDamageDone": 0,
              "trueDamageDoneToChampions": 0,
              "trueDamageTaken": 0
            },
            "goldPerSecond": 0,
            "jungleMinionsKilled": 0,
            "level": 1,
            "minionsKilled": 0,
            "participantId": 1,
            "position": {
              "x": 2191,
              "y": 11650
            },
            "timeEnemySpentControlled": 0,
            "totalGold": 500,
            "xp": 0
          },
          "2": {
            "championStats": {
              "abilityHaste": 0,
              "abilityPower": 0,
              "armor": 30,
              "armorPen": 0,
              "armorPenPercent": 0,
              "attackDamage": 78,
              "attackSpeed": 100,
              "bonusArmorPenPercent": 0,
              "bonusMagicPenPercent": 0,
              "ccReduction": 0,
              "cooldownReduction": 0,
              "health": 678,
              "healthMax": 723,
              "healthRegen": 17,
              "lifesteal": 0,
              "magicPen": 0,
              "magicPenPercent": 0,
              "magicResist": 36,
              "movementSpeed": 335,
              "omnivamp": 0,
              "physicalVamp": 0,
              "power": 352,
              "powerMax": 400,
              "powerRegen": 28,
              "spellVamp": 0
            },
            "currentGold": 50,
            "damageStats": {
              "magicDamageDone": 0,
              "magicDamageDoneToChampions": 0,
              "magicDamageTaken": 0,
              "physicalDamageDone": 824,
              "physicalDamageDoneToChampions": 37,
              "physicalDamageTaken": 69,
              "totalDamageDone": 1377,
              "totalDamageDoneToChampions": 37,
              "totalDamageTaken": 69,
              "trueDamageDone": 552,
              "trueDamageDoneToChampions": 0,
              "trueDamageTaken": 0
            },
            "goldPerSecond": 0,
            "jungleMinionsKilled": 0,
            "level": 1,
            "minionsKilled": 0,
            "participantId": 2,
            "position": {
              "x": 7000,
              "y": 4864
            },
            "timeEnemySpentControlled": 7014,
            "totalGold": 500,
            "xp": 0
          },
          "3": {
            "championStats": {
              "abilityHaste": 0,
              "abilityPower": 36,
              "armor": 22,
              "armorPen": 0,
              "armorPenPercent": 0,
              "attackDamage": 55,
              "attackSpeed": 100,
              "bonusArmorPenPercent": 0,
              "bonusMagicPenPercent": 0,
              "ccReduction": 0,
              "cooldownReduction": 0,
              "health": 576,
              "healthMax": 690,
              "healthRegen": 11,
              "lifesteal": 0,
              "magicPen": 0,
              "magicPenPercent": 0,
              "magicResist": 30,
              "movementSpeed": 340,
              "omnivamp": 0,
              "physicalVamp": 0,
              "power": 457,
              "powerMax": 494,
              "powerRegen": 16,
              "spellVamp": 0
            },
            "currentGold": 0,
            "damageStats": {
              "magicDamageDone": 131,
              "magicDamageDoneToChampions": 131,
              "magicDamageTaken": 0,
              "physicalDamageDone": 265,
              "physicalDamageDoneToChampions": 85,
              "physicalDamageTaken": 142,
              "totalDamageDone": 396,
              "totalDamageDoneToChampions": 216,
              "totalDamageTaken": 142,
              "trueDamageDone": 0,
              "trueDamageDoneToChampions": 0,
              "trueDamageTaken": 0
            },
            "goldPerSecond": 0,
            "jungleMinionsKilled": 0,
            "level": 1,
            "minionsKilled": 0,
            "participantId": 3,
            "position": {
              "x": 7057,
              "y": 7003
            },
            "timeEnemySpentControlled": 901,
            "totalGold": 500,
            "xp": 0
          },
          "4": {
            "championStats": {
              "abilityHaste": 0,
              "abilityPower": 0,
              "armor": 32,
              "armorPen": 0,
              "armorPenPercent": 0,
              "attackDamage": 65,
              "attackSpeed": 113,
              "bonusArmorPenPercent": 0,
              "bonusMagicPenPercent": 0,
              "ccReduction": 0,
              "cooldownReduction": 0,
              "health": 600,
              "healthMax": 600,
              "healthRegen": 13,
              "lifesteal": 0,
              "magicPen": 0,
              "magicPenPercent": 0,
              "magicResist": 32,
              "movementSpeed": 842,
              "omnivamp": 0,
              "physicalVamp": 0,
              "power": 131,
              "powerMax": 131,
              "powerRegen": 0,
              "spellVamp": 0
            },
            "currentGold": 500,
            "damageStats": {
              "magicDamageDone": 0,
              "magicDamageDoneToChampions": 0,
              "magicDamageTaken": 0,
              "physicalDamageDone": 0,
              "physicalDamageDoneToChampions": 0,
              "physicalDamageTaken": 0,
              "totalDamageDone": 0,
              "totalDamageDoneToChampions": 0,
              "totalDamageTaken": 0,
              "trueDamageDone": 0,
              "trueDamageDoneToChampions": 0,
              "trueDamageTaken": 0
            },
            "goldPerSecond": 0,
            "jungleMinionsKilled": 0,
            "level": 1,
            "minionsKilled": 0,
            "participantId": 4,
            "position": {
              "x": 130,
              "y": 401
            },
            "timeEnemySpentControlled": 0,
            "totalGold": 500,
            "xp": 0
          },
          "5": {
            "championStats": {
              "abilityHaste": 0,
              "abilityPower": 9,
              "armor": 26,
              "armorPen": 0,
              "armorPenPercent": 0,
              "attackDamage": 50,
              "attackSpeed": 100,
              "bonusArmorPenPercent": 0,
              "bonusMagicPenPercent": 0,
              "ccReduction": 0,
              "cooldownReduction": 0,
              "health": 610,
              "healthMax": 610,
              "healthRegen": 16,
              "lifesteal": 0,
              "magicPen": 0,
              "magicPenPercent": 0,
              "magicResist": 30,
              "movementSpeed": 330,
              "omnivamp": 0,
              "physicalVamp": 0,
              "power": 360,
              "powerMax": 360,
              "powerRegen": 28,
              "spellVamp": 0
            },
            "currentGold": 0,
            "damageStats": {
              "magicDamageDone": 0,
              "magicDamageDoneToChampions": 0,
              "magicDamageTaken": 0,
              "physicalDamageDone": 0,
              "physicalDamageDoneToChampions": 0,
              "physicalDamageTaken": 0,
              "totalDamageDone": 0,
              "totalDamageDoneToChampions": 0,
              "totalDamageTaken": 0,
              "trueDamageDone": 0,
              "trueDamageDoneToChampions": 0,
              "trueDamageTaken": 0
            },
            "goldPerSecond": 30,
            "jungleMinionsKilled": 0,
            "level": 1,
            "minionsKilled": 0,
            "participantId": 5,
            "position": {
              "x": 11522,
              "y": 1777
            },
            "timeEnemySpentControlled": 0,
            "totalGold": 500,
            "xp": 0
          },
          "6": {
            "championStats": {
              "abilityHaste": 0,
              "abilityPower": 36,
              "armor": 40,
              "armorPen": 0,
              "armorPenPercent": 0,
              "attackDamage": 62,
              "attackSpeed": 100,
              "bonusArmorPenPercent": 0,
              "bonusMagicPenPercent": 0,
              "ccReduction": 0,
              "cooldownReduction": 0,
              "health": 762,
              "healthMax": 765,
              "healthRegen": 14,
              "lifesteal": 0,
              "magicPen": 0,
              "magicPenPercent": 0,
              "magicResist": 28,
              "movementSpeed": 335,
              "omnivamp": 0,
              "physicalVamp": 0,
              "power": 280,
              "powerMax": 280,
              "powerRegen": 14,
              "spellVamp": 0
            },
            "currentGold": 0,
            "damageStats": {
              "magicDamageDone": 0,
              "magicDamageDoneToChampions": 0,
              "magicDamageTaken": 26,
              "physicalDamageDone": 0,
              "physicalDamageDoneToChampions": 0,
              "physicalDamageTaken": 0,
              "totalDamageDone": 0,
              "totalDamageDoneToChampions": 0,
              "totalDamageTaken": 26,
              "trueDamageDone": 0,
              "trueDamageDoneToChampions": 0,
              "trueDamageTaken": 0
            },
            "goldPerSecond": 0,
            "jungleMinionsKilled": 0,
            "level": 1,
            "minionsKilled": 0,
            "participantId": 6,
            "position": {
              "x": 1694,
              "y": 12864
            },
            "timeEnemySpentControlled": 0,
            "totalGold": 500,
            "xp": 0
          },
          "7": {
            "championStats": {
              "abilityHaste": 0,
              "abilityPower": 0,
              "armor": 38,
              "armorPen": 0,
              "armorPenPercent": 0,
              "attackDamage": 78,
              "attackSpeed": 100,
              "bonusArmorPenPercent": 0,
              "bonusMagicPenPercent": 0,
              "ccReduction": 0,
              "cooldownReduction": 0,
              "health": 669,
              "healthMax": 720,
              "healthRegen": 16,
              "lifesteal": 0,
              "magicPen": 0,
              "magicPenPercent": 0,
              "magicResist": 32,
              "movementSpeed": 340,
              "omnivamp": 0,
              "physicalVamp": 0,
              "power": 382,
              "powerMax": 410,
              "powerRegen": 30,
              "spellVamp": 0
            },
            "currentGold": 55,
            "damageStats": {
              "magicDamageDone": 0,
              "magicDamageDoneToChampions": 0,
              "magicDamageTaken": 0,
              "physicalDamageDone": 375,
              "physicalDamageDoneToChampions": 0,
              "physicalDamageTaken": 73,
              "totalDamageDone": 444,
              "totalDamageDoneToChampions": 0,
              "totalDamageTaken": 73,
              "trueDamageDone": 69,
              "trueDamageDoneToChampions": 0,
              "trueDamageTaken": 0
            },
            "goldPerSecond": 0,
            "jungleMinionsKilled": 0,
            "level": 1,
            "minionsKilled": 0,
            "participantId": 7,
            "position": {
              "x": 6585,
              "y": 11521
            },
            "timeEnemySpentControlled": 768,
            "totalGold": 505,
            "xp": 0
          },
          "8": {
            "championStats": {
              "abilityHaste": 0,
              "abilityPower": 0,
              "armor": 34,
              "armorPen": 0,
              "armorPenPercent": 0,
              "attackDamage": 67,
              "attackSpeed": 110,
              "bonusArmorPenPercent": 0,
              "bonusMagicPenPercent": 0,
              "ccReduction": 14,
              "cooldownReduction": 0,
              "health": 619,
              "healthMax": 770,
              "healthRegen": 26,
              "lifesteal": 12,
              "magicPen": 0,
              "magicPenPercent": 0,
              "magicResist": 32,
              "movementSpeed": 350,
              "omnivamp": 0,
              "physicalVamp": 0,
              "power": 326,
              "powerMax": 326,
              "powerRegen": 14,
              "spellVamp": 0
            },
            "currentGold": 0,
            "damageStats": {
              "magicDamageDone": 0,
              "magicDamageDoneToChampions": 0,
              "magicDamageTaken": 131,
              "physicalDamageDone": 142,
              "physicalDamageDoneToChampions": 142,
              "physicalDamageTaken": 123,
              "totalDamageDone": 142,
              "totalDamageDoneToChampions": 142,
              "totalDamageTaken": 254,
              "trueDamageDone": 0,
              "trueDamageDoneToChampions": 0,
              "trueDamageTaken": 0
            },
            "goldPerSecond": 0,
            "jungleMinionsKilled": 0,
            "level": 1,
            "minionsKilled": 0,
            "participantId": 8,
            "position": {
              "x": 7725,
              "y": 7567
            },
            "timeEnemySpentControlled": 0,
            "totalGold": 500,
            "xp": 0
          },
          "9": {
            "championStats": {
              "abilityHaste": 0,
              "abilityPower": 0,
              "armor": 27,
              "armorPen": 0,
              "armorPenPercent": 0,
              "attackDamage": 67,
              "attackSpeed": 113,
              "bonusArmorPenPercent": 0,
              "bonusMagicPenPercent": 0,
              "ccReduction": 0,
              "cooldownReduction": 0,
              "health": 755,
              "healthMax": 755,
              "healthRegen": 11,
              "lifesteal": 0,
              "magicPen": 0,
              "magicPenPercent": 0,
              "magicResist": 30,
              "movementSpeed": 325,
              "omnivamp": 2,
              "physicalVamp": 0,
              "power": 350,
              "powerMax": 350,
              "powerRegen": 14,
              "spellVamp": 0
            },
            "currentGold": 0,
            "damageStats": {
              "magicDamageDone": 0,
              "magicDamageDoneToChampions": 0,
              "magicDamageTaken": 0,
              "physicalDamageDone": 0,
              "physicalDamageDoneToChampions": 0,
              "physicalDamageTaken": 0,
              "totalDamageDone": 0,
              "totalDamageDoneToChampions": 0,
              "totalDamageTaken": 0,
              "trueDamageDone": 0,
              "trueDamageDoneToChampions": 0,
              "trueDamageTaken": 0
            },
            "goldPerSecond": 0,
            "jungleMinionsKilled": 0,
            "level": 1,
            "minionsKilled": 0,
            "participantId": 9,
            "position": {
              "x": 13054,
              "y": 2698
            },
            "timeEnemySpentControlled": 0,
            "totalGold": 500,
            "xp": 0
          },
          "10": {
            "championStats": {
              "abilityHaste": 0,
              "abilityPower": 18,
              "armor": 29,
              "armorPen": 0,
              "armorPenPercent": 0,
              "attackDamage": 54,
              "attackSpeed": 100,
              "bonusArmorPenPercent": 0,
              "bonusMagicPenPercent": 0,
              "ccReduction": 0,
              "cooldownReduction": 0,
              "health": 600,
              "healthMax": 600,
              "healthRegen": 13,
              "lifesteal": 0,
              "magicPen": 0,
              "magicPenPercent": 0,
              "magicResist": 30,
              "movementSpeed": 335,
              "omnivamp": 0,
              "physicalVamp": 0,
              "power": 365,
              "powerMax": 365,
              "powerRegen": 28,
              "spellVamp": 0
            },
            "currentGold": 0,
            "damageStats": {
              "magicDamageDone": 0,
              "magicDamageDoneToChampions": 0,
              "magicDamageTaken": 0,
              "physicalDamageDone": 0,
              "physicalDamageDoneToChampions": 0,
              "physicalDamageTaken": 0,
              "totalDamageDone": 0,
              "totalDamageDoneToChampions": 0,
              "totalDamageTaken": 0,
              "trueDamageDone": 0,
              "trueDamageDoneToChampions": 0,
              "trueDamageTaken": 0
            },
            "goldPerSecond": 30,
            "jungleMinionsKilled": 0,
            "level": 1,
            "minionsKilled": 0,
            "participantId": 10,
            "position": {
              "x": 13285,
              "y": 2275
            },
            "timeEnemySpentControlled": 0,
            "totalGold": 500,
            "xp": 0
          }
        },
        "timestamp": 60027
      },
      {
        "events": [
          {
            "levelUpType": "NORMAL",
            "participantId": 9,
            "skillSlot": 2,
            "timestamp": 66696,
            "type": "SKILL_LEVEL_UP"
          },
          {
            "itemId": 2003,
            "participantId": 8,
            "timestamp": 67999,
            "type": "ITEM_DESTROYED"
          },
          {
            "itemId": 1055,
            "participantId": 4,
            "timestamp": 68968,
            "type": "ITEM_PURCHASED"
          },
          {
            "levelUpType": "NORMAL",
            "participantId": 5,
            "skillSlot": 3,
            "timestamp": 69135,
            "type": "SKILL_LEVEL_UP"
          },
          {
            "itemId": 2003,
            "participantId": 4,
            "timestamp": 69402,
            "type": "ITEM_PURCHASED"
          },
          {
            "level": 2,
            "participantId": 2,
            "timestamp": 71039,
            "type": "LEVEL_UP"
          },
          {
            "gameId": 5509711409,
            "realTimestamp": 1773163503190,
            "timestamp": 75548,
            "type": "GAME_END",
            "winningTeam": 200
          }
        ],
        "participantFrames": {
          "1": {
            "championStats": {
              "abilityHaste": 0,
              "abilityPower": 27,
              "armor": 23,
              "armorPen": 0,
              "armorPenPercent": 0,
              "attackDamage": 53,
              "attackSpeed": 110,
              "bonusArmorPenPercent": 0,
              "bonusMagicPenPercent": 0,
              "ccReduction": 0,
              "cooldownReduction": 0,
              "health": 664,
              "healthMax": 762,
              "healthRegen": 12,
              "lifesteal": 0,
              "magicPen": 0,
              "magicPenPercent": 0,
              "magicResist": 32,
              "movementSpeed": 335,
              "omnivamp": 0,
              "physicalVamp": 0,
              "power": 440,
              "powerMax": 525,
              "powerRegen": 16,
              "spellVamp": 0
            },
            "currentGold": 21,
            "damageStats": {
              "magicDamageDone": 249,
              "magicDamageDoneToChampions": 165,
              "magicDamageTaken": 84,
              "physicalDamageDone": 116,
              "physicalDamageDoneToChampions": 0,
              "physicalDamageTaken": 36,
              "totalDamageDone": 385,
              "totalDamageDoneToChampions": 185,
              "totalDamageTaken": 121,
              "trueDamageDone": 20,
              "trueDamageDoneToChampions": 20,
              "trueDamageTaken": 0
            },
            "goldPerSecond": 0,
            "jungleMinionsKilled": 0,
            "level": 1,
            "minionsKilled": 0,
            "participantId": 1,
            "position": {
              "x": 2150,
              "y": 12226
            },
            "timeEnemySpentControlled": 4676,
            "totalGold": 521,
            "xp": 0
          },
          "2": {
            "championStats": {
              "abilityHaste": 0,
              "abilityPower": 0,
              "armor": 33,
              "armorPen": 0,
              "armorPenPercent": 0,
              "attackDamage": 81,
              "attackSpeed": 102,
              "bonusArmorPenPercent": 0,
              "bonusMagicPenPercent": 0,
              "ccReduction": 0,
              "cooldownReduction": 0,
              "health": 672,
              "healthMax": 801,
              "healthRegen": 18,
              "lifesteal": 0,
              "magicPen": 0,
              "magicPenPercent": 0,
              "magicResist": 37,
              "movementSpeed": 335,
              "omnivamp": 0,
              "physicalVamp": 0,
              "power": 396,
              "powerMax": 426,
              "powerRegen": 24,
              "spellVamp": 0
            },
            "currentGold": 146,
            "damageStats": {
              "magicDamageDone": 0,
              "magicDamageDoneToChampions": 0,
              "magicDamageTaken": 0,
              "physicalDamageDone": 1835,
              "physicalDamageDoneToChampions": 37,
              "physicalDamageTaken": 270,
              "totalDamageDone": 4254,
              "totalDamageDoneToChampions": 37,
              "totalDamageTaken": 270,
              "trueDamageDone": 2419,
              "trueDamageDoneToChampions": 0,
              "trueDamageTaken": 0
            },
            "goldPerSecond": 0,
            "jungleMinionsKilled": 4,
            "level": 2,
            "minionsKilled": 0,
            "participantId": 2,
            "position": {
              "x": 6430,
              "y": 4561
            },
            "timeEnemySpentControlled": 10488,
            "totalGold": 596,
            "xp": 300
          },
          "3": {
            "championStats": {
              "abilityHaste": 0,
              "abilityPower": 36,
              "armor": 22,
              "armorPen": 0,
              "armorPenPercent": 0,
              "attackDamage": 55,
              "attackSpeed": 100,
              "bonusArmorPenPercent": 0,
              "bonusMagicPenPercent": 0,
              "ccReduction": 0,
              "cooldownReduction": 0,
              "health": 548,
              "healthMax": 690,
              "healthRegen": 11,
              "lifesteal": 0,
              "magicPen": 0,
              "magicPenPercent": 0,
              "magicResist": 30,
              "movementSpeed": 420,
              "omnivamp": 0,
              "physicalVamp": 0,
              "power": 494,
              "powerMax": 494,
              "powerRegen": 16,
              "spellVamp": 0
            },
            "currentGold": 61,
            "damageStats": {
              "magicDamageDone": 131,
              "magicDamageDoneToChampions": 131,
              "magicDamageTaken": 0,
              "physicalDamageDone": 429,
              "physicalDamageDoneToChampions": 129,
              "physicalDamageTaken": 188,
              "totalDamageDone": 561,
              "totalDamageDoneToChampions": 261,
              "totalDamageTaken": 188,
              "trueDamageDone": 0,
              "trueDamageDoneToChampions": 0,
              "trueDamageTaken": 0
            },
            "goldPerSecond": 0,
            "jungleMinionsKilled": 0,
            "level": 1,
            "minionsKilled": 2,
            "participantId": 3,
            "position": {
              "x": 6875,
              "y": 6544
            },
            "timeEnemySpentControlled": 901,
            "totalGold": 561,
            "xp": 186
          },
          "4": {
            "championStats": {
              "abilityHaste": 0,
              "abilityPower": 0,
              "armor": 32,
              "armorPen": 0,
              "armorPenPercent": 0,
              "attackDamage": 75,
              "attackSpeed": 113,
              "bonusArmorPenPercent": 0,
              "bonusMagicPenPercent": 0,
              "ccReduction": 0,
              "cooldownReduction": 0,
              "health": 680,
              "healthMax": 680,
              "healthRegen": 13,
              "lifesteal": 0,
              "magicPen": 0,
              "magicPenPercent": 0,
              "magicResist": 32,
              "movementSpeed": 773,
              "omnivamp": 2,
              "physicalVamp": 0,
              "power": 131,
              "powerMax": 131,
              "powerRegen": 0,
              "spellVamp": 0
            },
            "currentGold": 21,
            "damageStats": {
              "magicDamageDone": 0,
              "magicDamageDoneToChampions": 0,
              "magicDamageTaken": 0,
              "physicalDamageDone": 0,
              "physicalDamageDoneToChampions": 0,
              "physicalDamageTaken": 0,
              "totalDamageDone": 0,
              "totalDamageDoneToChampions": 0,
              "totalDamageTaken": 0,
              "trueDamageDone": 0,
              "trueDamageDoneToChampions": 0,
              "trueDamageTaken": 0
            },
            "goldPerSecond": 0,
            "jungleMinionsKilled": 0,
            "level": 1,
            "minionsKilled": 0,
            "participantId": 4,
            "position": {
              "x": 2549,
              "y": 1305
            },
            "timeEnemySpentControlled": 0,
            "totalGold": 521,
            "xp": 0
          },
          "5": {
            "championStats": {
              "abilityHaste": 0,
              "abilityPower": 9,
              "armor": 26,
              "armorPen": 0,
              "armorPenPercent": 0,
              "attackDamage": 50,
              "attackSpeed": 100,
              "bonusArmorPenPercent": 0,
              "bonusMagicPenPercent": 0,
              "ccReduction": 0,
              "cooldownReduction": 0,
              "health": 610,
              "healthMax": 610,
              "healthRegen": 16,
              "lifesteal": 0,
              "magicPen": 0,
              "magicPenPercent": 0,
              "magicResist": 30,
              "movementSpeed": 330,
              "omnivamp": 0,
              "physicalVamp": 0,
              "power": 316,
              "powerMax": 385,
              "powerRegen": 28,
              "spellVamp": 0
            },
            "currentGold": 24,
            "damageStats": {
              "magicDamageDone": 84,
              "magicDamageDoneToChampions": 84,
              "magicDamageTaken": 0,
              "physicalDamageDone": 0,
              "physicalDamageDoneToChampions": 0,
              "physicalDamageTaken": 0,
              "totalDamageDone": 84,
              "totalDamageDoneToChampions": 84,
              "totalDamageTaken": 0,
              "trueDamageDone": 0,
              "trueDamageDoneToChampions": 0,
              "trueDamageTaken": 0
            },
            "goldPerSecond": 30,
            "jungleMinionsKilled": 0,
            "level": 1,
            "minionsKilled": 0,
            "participantId": 5,
            "position": {
              "x": 10217,
              "y": 1357
            },
            "timeEnemySpentControlled": 2538,
            "totalGold": 524,
            "xp": 0
          },
          "6": {
            "championStats": {
              "abilityHaste": 0,
              "abilityPower": 36,
              "armor": 40,
              "armorPen": 0,
              "armorPenPercent": 0,
              "attackDamage": 62,
              "attackSpeed": 100,
              "bonusArmorPenPercent": 0,
              "bonusMagicPenPercent": 0,
              "ccReduction": 0,
              "cooldownReduction": 0,
              "health": 575,
              "healthMax": 765,
              "healthRegen": 21,
              "lifesteal": 0,
              "magicPen": 0,
              "magicPenPercent": 0,
              "magicResist": 28,
              "movementSpeed": 335,
              "omnivamp": 0,
              "physicalVamp": 0,
              "power": 235,
              "powerMax": 305,
              "powerRegen": 14,
              "spellVamp": 0
            },
            "currentGold": 21,
            "damageStats": {
              "magicDamageDone": 84,
              "magicDamageDoneToChampions": 84,
              "magicDamageTaken": 165,
              "physicalDamageDone": 201,
              "physicalDamageDoneToChampions": 0,
              "physicalDamageTaken": 45,
              "totalDamageDone": 285,
              "totalDamageDoneToChampions": 84,
              "totalDamageTaken": 231,
              "trueDamageDone": 0,
              "trueDamageDoneToChampions": 0,
              "trueDamageTaken": 20
            },
            "goldPerSecond": 0,
            "jungleMinionsKilled": 0,
            "level": 1,
            "minionsKilled": 0,
            "participantId": 6,
            "position": {
              "x": 2198,
              "y": 11586
            },
            "timeEnemySpentControlled": 6747,
            "totalGold": 521,
            "xp": 0
          },
          "7": {
            "championStats": {
              "abilityHaste": 0,
              "abilityPower": 0,
              "armor": 38,
              "armorPen": 0,
              "armorPenPercent": 0,
              "attackDamage": 78,
              "attackSpeed": 100,
              "bonusArmorPenPercent": 0,
              "bonusMagicPenPercent": 0,
              "ccReduction": 0,
              "cooldownReduction": 0,
              "health": 565,
              "healthMax": 720,
              "healthRegen": 16,
              "lifesteal": 0,
              "magicPen": 0,
              "magicPenPercent": 0,
              "magicResist": 32,
              "movementSpeed": 340,
              "omnivamp": 0,
              "physicalVamp": 0,
              "power": 354,
              "powerMax": 410,
              "powerRegen": 38,
              "spellVamp": 0
            },
            "currentGold": 76,
            "damageStats": {
              "magicDamageDone": 0,
              "magicDamageDoneToChampions": 0,
              "magicDamageTaken": 0,
              "physicalDamageDone": 1152,
              "physicalDamageDoneToChampions": 0,
              "physicalDamageTaken": 285,
              "totalDamageDone": 1497,
              "totalDamageDoneToChampions": 0,
              "totalDamageTaken": 285,
              "trueDamageDone": 345,
              "trueDamageDoneToChampions": 0,
              "trueDamageTaken": 0
            },
            "goldPerSecond": 0,
            "jungleMinionsKilled": 0,
            "level": 1,
            "minionsKilled": 0,
            "participantId": 7,
            "position": {
              "x": 6999,
              "y": 11199
            },
            "timeEnemySpentControlled": 768,
            "totalGold": 526,
            "xp": 0
          },
          "8": {
            "championStats": {
              "abilityHaste": 0,
              "abilityPower": 0,
              "armor": 34,
              "armorPen": 0,
              "armorPenPercent": 0,
              "attackDamage": 67,
              "attackSpeed": 110,
              "bonusArmorPenPercent": 0,
              "bonusMagicPenPercent": 0,
              "ccReduction": 14,
              "cooldownReduction": 0,
              "health": 716,
              "healthMax": 770,
              "healthRegen": 113,
              "lifesteal": 12,
              "magicPen": 0,
              "magicPenPercent": 0,
              "magicResist": 32,
              "movementSpeed": 350,
              "omnivamp": 0,
              "physicalVamp": 0,
              "power": 305,
              "powerMax": 326,
              "powerRegen": 14,
              "spellVamp": 0
            },
            "currentGold": 41,
            "damageStats": {
              "magicDamageDone": 0,
              "magicDamageDoneToChampions": 0,
              "magicDamageTaken": 131,
              "physicalDamageDone": 441,
              "physicalDamageDoneToChampions": 142,
              "physicalDamageTaken": 167,
              "totalDamageDone": 441,
              "totalDamageDoneToChampions": 142,
              "totalDamageTaken": 298,
              "trueDamageDone": 0,
              "trueDamageDoneToChampions": 0,
              "trueDamageTaken": 0
            },
            "goldPerSecond": 0,
            "jungleMinionsKilled": 0,
            "level": 1,
            "minionsKilled": 1,
            "participantId": 8,
            "position": {
              "x": 7241,
              "y": 7649
            },
            "timeEnemySpentControlled": 0,
            "totalGold": 541,
            "xp": 62
          },
          "9": {
            "championStats": {
              "abilityHaste": 0,
              "abilityPower": 0,
              "armor": 27,
              "armorPen": 0,
              "armorPenPercent": 0,
              "attackDamage": 67,
              "attackSpeed": 113,
              "bonusArmorPenPercent": 0,
              "bonusMagicPenPercent": 0,
              "ccReduction": 0,
              "cooldownReduction": 0,
              "health": 755,
              "healthMax": 755,
              "healthRegen": 11,
              "lifesteal": 0,
              "magicPen": 0,
              "magicPenPercent": 0,
              "magicResist": 30,
              "movementSpeed": 325,
              "omnivamp": 2,
              "physicalVamp": 0,
              "power": 282,
              "powerMax": 350,
              "powerRegen": 14,
              "spellVamp": 0
            },
            "currentGold": 61,
            "damageStats": {
              "magicDamageDone": 506,
              "magicDamageDoneToChampions": 0,
              "magicDamageTaken": 0,
              "physicalDamageDone": 269,
              "physicalDamageDoneToChampions": 0,
              "physicalDamageTaken": 0,
              "totalDamageDone": 829,
              "totalDamageDoneToChampions": 0,
              "totalDamageTaken": 0,
              "trueDamageDone": 53,
              "trueDamageDoneToChampions": 0,
              "trueDamageTaken": 0
            },
            "goldPerSecond": 0,
            "jungleMinionsKilled": 0,
            "level": 1,
            "minionsKilled": 2,
            "participantId": 9,
            "position": {
              "x": 10701,
              "y": 1644
            },
            "timeEnemySpentControlled": 0,
            "totalGold": 561,
            "xp": 80
          },
          "10": {
            "championStats": {
              "abilityHaste": 0,
              "abilityPower": 18,
              "armor": 29,
              "armorPen": 0,
              "armorPenPercent": 0,
              "attackDamage": 54,
              "attackSpeed": 100,
              "bonusArmorPenPercent": 0,
              "bonusMagicPenPercent": 0,
              "ccReduction": 0,
              "cooldownReduction": 0,
              "health": 184,
              "healthMax": 600,
              "healthRegen": 13,
              "lifesteal": 0,
              "magicPen": 0,
              "magicPenPercent": 0,
              "magicResist": 30,
              "movementSpeed": 335,
              "omnivamp": 0,
              "physicalVamp": 0,
              "power": 309,
              "powerMax": 365,
              "powerRegen": 28,
              "spellVamp": 0
            },
            "currentGold": 44,
            "damageStats": {
              "magicDamageDone": 8,
              "magicDamageDoneToChampions": 0,
              "magicDamageTaken": 84,
              "physicalDamageDone": 54,
              "physicalDamageDoneToChampions": 0,
              "physicalDamageTaken": 403,
              "totalDamageDone": 62,
              "totalDamageDoneToChampions": 0,
              "totalDamageTaken": 487,
              "trueDamageDone": 0,
              "trueDamageDoneToChampions": 0,
              "trueDamageTaken": 0
            },
            "goldPerSecond": 30,
            "jungleMinionsKilled": 0,
            "level": 1,
            "minionsKilled": 0,
            "participantId": 10,
            "position": {
              "x": 10927,
              "y": 1518
            },
            "timeEnemySpentControlled": 0,
            "totalGold": 544,
            "xp": 80
          }
        },
        "timestamp": 75548
      }
    ],
    "gameId": 5509711409,
    "participants": [
      {
        "participantId": 1,
        "puuid": "APA28lrTMAindqS2JtK37LpHssR84c5yA-rsROWLMl0lUibJqj-h3eJGCCdLYzi2F5TVI1puEFg29A"
      },
      {
        "participantId": 2,
        "puuid": "C9cqY_f7CKLenYtaF88zJIDoOeKjsA0Tlm1c5zwYo-gsr1s0Dz_017Y6yO7q0poClRP9d1LihtZUKQ"
      },
      {
        "participantId": 3,
        "puuid": "dgLaMbNO-4i_tjq3CxrBD7rt0Vd3352ekzoX8YrqYyMHd53ZQhl_cRv2m_k0Tbrlmz6MGTMerz3rtg"
      },
      {
        "participantId": 4,
        "puuid": "y6dT8B0hQr_O9RAGcPesmwDLfgbggO2QVllgr8WoWUFkPhyuUuVnO-aK-bEDQtMLZ-hOrRfZoomlCg"
      },
      {
        "participantId": 5,
        "puuid": "uOeA9Vr1KWCfS8423pKuTp4BvX6KHCYj2tVRzshc6HKRGCTTAEUe2sgmJGIJxdWLSZ3gIrqak560-w"
      },
      {
        "participantId": 6,
        "puuid": "3tYeKv0VM46d3uIXQAzdZM-lrcdAN0bkSE4DYPNkkzRRc4NzoH7X_Hjz7u_0R8qyQqMP2DCUz3ergg"
      },
      {
        "participantId": 7,
        "puuid": "QvvuKSyYjC8oDYdsdCaI-e7pjK8s-t4XObnsdmRHRGntC6eVybdawIB0_HdfBI0UOe0gysX-GH63Ng"
      },
      {
        "participantId": 8,
        "puuid": "aJRqb8vC0me7j4Ovn_yLs98-oO2oLsbBTmEyrKVCGRQM_AoHWPLIyHF5giged-eJ6k4sxeaDscYIzA"
      },
      {
        "participantId": 9,
        "puuid": "eLsvz5Jk0dgoQifrZL6IlXr30qpNjoMAo5-L7jNqdM8zSjUGTebwUgIKvwWKFb7vp48MhevPsgZZaQ"
      },
      {
        "participantId": 10,
        "puuid": "rOmEEynItfQpKDMyxFt5nVkn6xmv_fdy3CuJrbD0D-CFT5YFLkng3xUvkMuIgD9RuEgHbcet7ky4cw"
      }
    ]
  }
}